.DS_Store
avacado_messenger-0.1.2.dist-info/DESCRIPTION.rst
avacado_messenger-0.1.2.dist-info/METADATA
avacado_messenger-0.1.2.dist-info/RECORD
avacado_messenger-0.1.2.dist-info/WHEEL
avacado_messenger-0.1.2.dist-info/entry_points.txt
avacado_messenger-0.1.2.dist-info/metadata.json
avacado_messenger-0.1.2.dist-info/top_level.txt
client/__init__.py
client/bd_client_app.py
client/client.py
client/client.sqlite
client/gui_app_client.py
client/log_config.py
client/message.svg
client/user.svg
jim/__init__.py
jim/common_classes.py
jim/config.py
jim/test.py
server/__init__.py
server/bd_server_app.py
server/log_config.py
server/server.py
server/server.sqlite
