Metadata-Version: 2.0
Name: avacado-messenger
Version: 0.1.2
Summary: Server for short text messanger
Home-page: https://github.com/chud0/messenger
Author: chud0
Author-email: www.chud0@mail.ru
License: UNKNOWN
Platform: UNKNOWN
Classifier: Development Status :: 3 - Alpha
Classifier: Programming Language :: Python :: 3.6
Requires-Python: >=3
Requires-Dist: SQLAlchemy
